git_identity/__init__.py
git_identity/__main__.py
git_identity-1.0.1.dist-info/entry_points.txt
git_identity-1.0.1.dist-info/WHEEL
git_identity-1.0.1.dist-info/METADATA
git_identity-1.0.1.dist-info/RECORD
