Metadata-Version: 2.1
Name: git-identity
Version: 1.0.1
Summary: Quickly set user.name and user.email for a repository, based on a config file
Home-page: https://github.com/aatifsyed/git-identity
License: MIT
Author: Aatif Syed
Author-email: aatifsyedyp@gmail.com
Requires-Python: >=3.8,<4.0
Classifier: License :: OSI Approved :: MIT License
Classifier: Programming Language :: Python :: 3
Classifier: Programming Language :: Python :: 3.8
Classifier: Programming Language :: Python :: 3.9
Requires-Dist: GitPython (>=3.1.18,<4.0.0)
Requires-Dist: argcomplete (>=1.12.3,<2.0.0)
Requires-Dist: dataclasses-json (>=0.5.4,<0.6.0)
Requires-Dist: jsonschema (>=3.2.0,<4.0.0)
Requires-Dist: logging-actions (>=0.1.6,<0.2.0)
Requires-Dist: xdg (>=5.1.0,<6.0.0)
Project-URL: Repository, https://github.com/aatifsyed/git-identity
